CLK Gen/oscillator_400K.sv

// Module for the simulated oscillator
module oscillator_400K(
    global_if glb, 
    output logic clk_400K
);

// Set timescale
timeunit 1ns;
timeprecision 1ps;

parameter real PERIOD = 2500.0; // In nanoseconds

initial clk_400K = 0;

always begin
    if (!glb.sleep)
        #(PERIOD/2) clk_400K = ~clk_400K;
    else begin
        clk_400K = 0;
        @(negedge glb.sleep);
    end
end

endmodule

FULL SYS/led_driver.sv
// Main Module
module led_driver(
    input logic reset,
    input logic scl,
    inout wire  sda,
    output logic [3:0] leds
);

// Power-on-Reset

// oscillator
    logic clk_osc;  // internal 400 kHz clock for LED timing

    // oscillator module
    oscillator_400K u_osc (
        .glb      (glb),
        .clk_400K (clk_osc)
    );

// led_controller
    
    // From I2C bus interface → I2C controller
    logic  [7:0] i2c_byte;       // received I2C byte
    logic        i2c_byte_valid; // pulse when a new byte is available

    // Register interface between I2C controller and LED controller
    logic [2:0] reg_addr;        // 3-bit address (0x0–0x7)
    logic [7:0] reg_wdata;       // data to write
    logic [7:0] reg_rdata;       // data read
    logic       reg_write;       // write strobe
    logic       reg_read;        // read strobe

    // Sleep bit from MODE register (bit 4)
    logic       sleep;

// i2c instantiation

endmodule

FULL SYS/testbench/led_driver_tb.sv
import led_driver_pkg::*;


// Testbench for LED Driver (Main Module)
module led_controller_tb;

// Set timescale
timeunit 1ms;
timeprecision 10ns;


// Declare port connections & interfaces
logic [3:0] LEDS;
logic RESET;
logic SCL;
wire  SDA;
logic sda_out;   // SDA value driven by TB
logic sda_oe;    // SDA output enable: 1 = drive, 0 = release

assign SDA = sda_oe ? sda_out : 1'bz;


// Instantiate DUT
led_driver DUT(
    .leds(LEDS),
    .reset(RESET),
    .scl(SCL),
    .sda(SDA)
);
// keep track of writes for self-checking
logic [ADDR_BITS-1:0] last_addr;
logic [DATA_BITS-1:0] last_data;
logic                 last_we;

always @(posedge DUT.bus.w_en) begin
    last_addr <= DUT.bus.addr;
    last_data <= DUT.bus.data;
    last_we   <= 1'b1;
end


logic __end; // Special var for flagging end of sim
int error_count = 0; // for testbench self-checking
// Task for flagging the end of simulation
task end_sim();
    __end = 0; #1;
    __end = 1; #1;
    $dumpflush;
endtask


// Task for reseting the DUT
task reset_dut();
    #0.0025 RESET = 1; 
    #0.0025 RESET = 0;
    $display("[Reset]");
endtask


localparam logic [6:0] I2C_ADDR = 7'h40;  // Must match DEVICE_ADDR in i2c_controller
localparam real        T_I2C    = 0.01; // Half I2C bit time with timeunit 1ms

task automatic i2c_start();
    sda_oe  = 1'b1;
    sda_out = 1'b1;
    SCL     = 1'b1;
    #T_I2C;
    sda_out = 1'b0; // SDA 1->0 while SCL=1
    #T_I2C;
endtask

task automatic i2c_stop();
    sda_oe  = 1'b1;
    sda_out = 1'b0;
    SCL     = 1'b1;
    #T_I2C;
    sda_out = 1'b1; // SDA 0->1 while SCL=1
    #T_I2C;
endtask

task automatic i2c_write_byte(input logic [7:0] data);
    int i;
    for (i = 7; i >= 0; i--) begin
        SCL     = 1'b0;
        sda_oe  = 1'b1;
        sda_out = data[i];
        #T_I2C;
        SCL     = 1'b1;
        #T_I2C;
    end
    // No ACK Cycle
endtask

task automatic i2c_read_byte(output logic [7:0] data);
    int  i;
    logic bit_val;
    data = '0;
    for (i = 7; i >= 0; i--) begin
        SCL    = 1'b0;
        sda_oe = 1'b0; // release SDA so slave can drive
        #T_I2C;
        SCL    = 1'b1;
        #T_I2C;
        bit_val = SDA;
        data[i] = bit_val;
    end
    // No ACK/NACK cycle
endtask

task automatic i2c_write_reg_raw(input reg_enum_t a, input logic [DATA_BITS-1:0] d);
    logic [7:0] addr_byte;
    logic [7:0] reg_byte;
    addr_byte = {I2C_ADDR, 1'b0};                    // 7-bit addr + W
    reg_byte  = {{(8-ADDR_BITS){1'b0}}, a};          // zero-extend reg index

    i2c_start();
    i2c_write_byte(addr_byte);
    i2c_write_byte(reg_byte);
    i2c_write_byte(d);
    i2c_stop();
endtask

task automatic i2c_read_reg_raw(input reg_enum_t a, output logic [DATA_BITS-1:0] d);
    logic [7:0] addr_byte;
    logic [7:0] reg_byte;
    logic [7:0] tmp;
    addr_byte = {I2C_ADDR, 1'b1};                    // 7-bit addr + R
    reg_byte  = {{(8-ADDR_BITS){1'b0}}, a};

    i2c_start();
    i2c_write_byte(addr_byte);
    i2c_write_byte(reg_byte);
    i2c_read_byte(tmp);
    i2c_stop();

    d = tmp;
endtask

// Task for writing to a register in the LED controller
task write_reg(input reg_enum_t a, input logic [DATA_BITS-1:0] d);
    logic [ADDR_BITS-1:0] exp_addr;

    exp_addr = a;

    i2c_write_reg_raw(a, d);

    // small delay to let controller update bus
    #0.001;

    if (!last_we) begin
        $error("[Write-Check FAIL] %s no write observed on bus_if", a.name());
        error_count++;
    end
    else if (last_addr !== exp_addr || last_data !== d) begin
        $error("[Write-Check FAIL] %s expected addr=%0d data=%b got addr=%0d data=%b",
               a.name(), exp_addr, d, last_addr, last_data);
        error_count++;
    end
    else begin
        $display("[Write-Check PASS]\t%s\taddr=%0d data=%b", a.name(), last_addr, last_data);
    end

    last_we = 1'b0;
endtask

// Task for reading a register in the LED controller
task read_reg(input reg_enum_t a);
    logic [DATA_BITS-1:0] d;
    i2c_read_reg_raw(a, d);
    $display("[Read]\t%s\t\tDATA=%b", a.name(), d);
endtask

// Test LED ON output
task test_on();
    $display("\n-- LEDs On (No PWM) --");
    write_reg(REG_LEDOUT, 8'h55);       // Turn LEDs to fully on (no PWM)
    #1s;
endtask

// Test individual PWM output
task test_indiv();
    $display("\n-- Individual PWM --");
    write_reg(REG_LEDOUT, 8'hAA);       // Turn LEDs to individual mode
    #1s;
    write_reg(REG_PWM0, 8'h40);         // Set PWM0 channel to 25%
    write_reg(REG_PWM1, 8'h80);         // Set PWM1 channel to 50%
    write_reg(REG_PWM2, 8'hC0);         // Set PWM2 channel to 75%
    write_reg(REG_PWM3, 8'hFF);         // Set PWM3 channel to 99%
    #1s;
    write_reg(REG_PWM0, 8'hb2);         // Set PWM0 channel to 69.5%
    #1s;
    write_reg(REG_PWM1, 8'h01);         // Set PWM1 channel to 0.4%
    #1s;
    write_reg(REG_PWM2, 8'hE7);         // Set PWM2 channel to 90.2%
    #1s;
    write_reg(REG_PWM3, 8'h33);         // Set PWM3 channel to 20%
    #1s;
endtask

// Test group dimming mode
task test_grp_dim();
    $display("\n-- Group Dimming --");
    write_reg(REG_LEDOUT, 8'hFF);       // Turn LEDs to group mode
    write_reg(REG_GRPPWM, 8'hC0);       // Set group PWM to 75%
    #1s;
    write_reg(REG_PWM3, 8'h40);         // Set PWM3 channel to 25%
    write_reg(REG_PWM2, 8'h80);         // Set PWM2 channel to 50%
    write_reg(REG_PWM1, 8'hC0);         // Set PWM1 channel to 75%
    write_reg(REG_PWM0, 8'hFF);         // Set PWM0 channel to 99%
    #1s;
    write_reg(REG_GRPPWM, 8'h00);       // Set group PWM to 0%
    #1s;
    write_reg(REG_GRPPWM, 8'h80);       // Set group PWM to 50%
    #1s;
    write_reg(REG_GRPPWM, 8'h30);       // Set group PWM to 18.75%
    #1s;
endtask

// Test group blinking mode
task test_grp_blink();
    $display("\n-- Group Blinking --");
    write_reg(REG_LEDOUT, 8'hFF);       // Turn LEDs to group mode
    write_reg(REG_MODE, 8'h08);         // Set DMBLNK bit (GRPFREQ is zero by default so blink @24Hz)
    #1s;
    write_reg(REG_GRPPWM, 8'h80);       // Set group PWM to 50%
    #1s;
    write_reg(REG_GRPFREQ, 8'h10);      // Set group period to 656ms (1.524Hz) 
    #5s;
    write_reg(REG_GRPFREQ, 8'hFF);      // Set group period to max (10.5s - 0.09Hz) 
    #25s;
    write_reg(REG_MODE, 8'h00);         // Clear DMBLNK bit
    #1s;
endtask

// Test sleep
task test_sleep();
    $display("\n-- Sleep --");
    write_reg(REG_LEDOUT, 8'hAA);       // Turn LEDs to individual mode
    write_reg(REG_MODE, 8'h10);         // Set SLEEP bit
    #1s;
    write_reg(REG_MODE, 8'h00);         // Clear SLEEP bit
    #1s;
endtask

// Test inverting the output
task test_invert();
    $display("\n-- Invert Output --");
    write_reg(REG_LEDOUT, 8'hAA);       // Turn LEDs to individual mode
    write_reg(REG_MODE, 8'h04);         // Set INVRT bit
    #1s;
    write_reg(REG_MODE, 8'h00);         // Clear INVRT bit
    #1s;
endtask

// Test reading register values
task test_readback();
    $display("\n-- Register Read --");
    // Read PWM registers before & after reset
    read_reg(REG_PWM0);
    read_reg(REG_PWM1);
    read_reg(REG_PWM2);
    read_reg(REG_PWM3);
    reset_dut(); 
    #1s;
    read_reg(REG_PWM0);
    read_reg(REG_PWM1);
    read_reg(REG_PWM2);
    read_reg(REG_PWM3);
    #1s;
endtask

// Group all test tasks here
task test();
    $display("\n=== Starting Testcases ===\n");

    test_on();
    test_indiv();
    test_grp_dim();
    test_grp_blink();
    test_sleep();
    test_invert();
    test_readback();
    
    if (error_count == 0) begin
        $display("\n=== ALL TESTS PASSED ===");
    end else begin
        $display("\n=== TEST FAILED: %0d error(s) ===", error_count);
    end

    end_sim(); // Flag the end of sim
    $finish();
endtask

// Main intial block
initial begin
    // Zero everything out
    RESET   = 0;
    SCL     = 0;
    sda_oe  = 1'b1;
    sda_out = 1'b1;   // I2C idle: SDA high

    reset_dut();      // Reset before starting
    test();           // Run all tests
end

// Save the output file
initial begin
    $dumpfile("wave.vcd");
    $dumpvars(0, led_controller_tb.__end);
    $dumpvars(0, led_controller_tb.LEDS);
    
end

endmodule

wave.vcd
$date
	Sun Nov 30 12:58:26 2025
$end
$version
	QuestaSim Version 2025.2_1
$end
$timescale
	1ps
$end

$scope module led_controller_tb $end
$var reg 1 ! __end $end
$var reg 4 " LEDS [3:0] $end
$upscope $end
$enddefinitions $end
#0
$dumpvars
x!
bx "
$end
#2500000
b0 "
#1000033750000
b1111 "
#2000163750000
b1110 "
#2000323750000
b1100 "
#2000483750000
b1000 "
#2000641250000
b0 "
#2000643750000
b1111 "
#2000803750000
b1110 "
#2000963750000
b1100 "
#2001123750000
b1000 "
#2001281250000
b0 "
#2001283750000
b1111 "
#2001443750000
b1110 "
#2001603750000
b1100 "
#2001763750000
b1000 "
#2001921250000
b0 "
#2001923750000
b1111 "
#2002083750000
b1110 "
#2002243750000
b1100 "
#2002403750000
b1000 "
#2002561250000
b0 "
#2002563750000
b1111 "
#2002723750000
b1110 "
#2002883750000
b1100 "
#2003043750000
b1000 "
#2003201250000
b0 "
#2003203750000
b1111 "
#2003363750000
b1110 "
#2003523750000
b1100 "
#2003683750000
b1000 "
#2003841250000
b0 "
#2003843750000
b1111 "
#2004003750000
b1110 "
#2004163750000
b1100 "
#2004323750000
b1000 "
#2004481250000
b0 "
#2004483750000
b1111 "
#2004643750000
b1110 "
#2004803750000
b1100 "
#2004963750000
b1000 "
#2005121250000
b0 "
#2005123750000
b1111 "
#2005283750000
b1110 "
#2005443750000
b1100 "
#2005603750000
b1000 "
#2005761250000
b0 "
#2005763750000
b1111 "
#2005923750000
b1110 "
#2006083750000
b1100 "
#2006243750000
b1000 "
#2006401250000
b0 "
#2006403750000
b1111 "
#2006563750000
b1110 "
#2006723750000
b1100 "
#2006883750000
b1000 "
#2007041250000
b0 "
#2007043750000
b1111 "
#2007203750000
b1110 "
#2007363750000
b1100 "
#2007523750000
b1000 "
#2007681250000
b0 "
#2007683750000
b1111 "
#2007843750000
b1110 "
#2008003750000
b1100 "
#2008163750000
b1000 "
#2008321250000
b0 "
#2008323750000
b1111 "
#2008483750000
b1110 "
#2008643750000
b1100 "
#2008803750000
b1000 "
#2008961250000
b0 "
#2008963750000
b1111 "
#2009123750000
b1110 "
#2009283750000
b1100 "
#2009443750000
b1000 "
#2009601250000
b0 "
#2009603750000
b1111 "
#2009763750000
b1110 "
#2009923750000
b1100 "
#2010083750000
b1000 "
#2010241250000
b0 "
#2010243750000
b1111 "
#2010403750000
b1110 "
#2010563750000
b1100 "
#2010723750000
b1000 "
#2010881250000
b0 "
#2010883750000
b1111 "
#2011043750000
b1110 "
#2011203750000
b1100 "
#2011363750000
b1000 "
#2011521250000
b0 "
#2011523750000
b1111 "
#2011683750000
b1110 "
#2011843750000
b1100 "
#2012003750000
b1000 "
#2012161250000
b0 "
#2012163750000
b1111 "
#2012323750000
b1110 "
#2012483750000
b1100 "
#2012643750000
b1000 "
#2012801250000
b0 "
#2012803750000
b1111 "
#2012963750000
b1110 "
#2013123750000
b1100 "
#2013283750000
b1000 "
#2013441250000
b0 "
#2013443750000
b1111 "
#2013603750000
b1110 "
#2013763750000
b1100 "
#2013923750000
b1000 "
#2014081250000
b0 "
#2014083750000
b1111 "
#2014243750000
b1110 "
#2014403750000
b1100 "
#2014563750000
b1000 "
#2014721250000
b0 "
#2014723750000
b1111 "
#2014883750000
b1110 "
#2015043750000
b1100 "
#2015203750000
b1000 "
#2015361250000
b0 "
#2015363750000
b1111 "
#2015523750000
b1110 "
#2015683750000
b1100 "
#2015843750000
b1000 "
#2016001250000
b0 "
#2016003750000
b1111 "
#2016163750000
b1110 "
#2016323750000
b1100 "
#2016483750000
b1000 "
#2016641250000
b0 "
#2016643750000
b1111 "
#2016803750000
b1110 "
#2016963750000
b1100 "
#2017123750000
b1000 "
#2017281250000
b0 "
#2017283750000
b1111 "
#2017443750000
b1110 "
#2017603750000
b1100 "
#2017763750000
b1000 "
#2017921250000
b0 "
#2017923750000
b1111 "
#2018083750000
b1110 "
#2018243750000
b1100 "
#2018403750000
b1000 "
#2018561250000
b0 "
#2018563750000
b1111 "
#2018723750000
b1110 "
#2018883750000
b1100 "
#2019043750000
b1000 "
#2019201250000
b0 "
#2019203750000
b1111 "
#2019363750000
b1110 "
#2019523750000
b1100 "
#2019683750000
b1000 "
#2019841250000
b0 "
#2019843750000
b1111 "
#2020003750000
b1110 "
#2020163750000
b1100 "
#2020323750000
b1000 "
#2020481250000
b0 "
#2020483750000
b1111 "
#2020643750000
b1110 "
#2020803750000
b1100 "
#2020963750000
b1000 "
#2021121250000
b0 "
#2021123750000
b1111 "
#2021283750000
b1110 "
#2021443750000
b1100 "
#2021603750000
b1000 "
#2021761250000
b0 "
#2021763750000
b1111 "
#2021923750000
b1110 "
#2022083750000
b1100 "
#2022243750000
b1000 "
#2022401250000
b0 "
#2022403750000
b1111 "
#2022563750000
b1110 "
#2022723750000
b1100 "
#2022883750000
b1000 "
#2023041250000
b0 "
#2023043750000
b1111 "
#2023203750000
b1110 "
#2023363750000
b1100 "
#2023523750000
b1000 "
#2023681250000
b0 "
#2023683750000
b1111 "
#2023843750000
b1110 "
#2024003750000
b1100 "
#2024163750000
b1000 "
#2024321250000
b0 "
#2024323750000
b1111 "
#2024483750000
b1110 "
#2024643750000
b1100 "
#2024803750000
b1000 "
#2024961250000
b0 "
#2024963750000
b1111 "
#2025123750000
b1110 "
#2025283750000
b1100 "
#2025443750000
b1000 "
#2025601250000
b0 "
#2025603750000
b1111 "
#2025763750000
b1110 "
#2025923750000
b1100 "
#2026083750000
b1000 "
#2026241250000
b0 "
#2026243750000
b1111 "
#2026403750000
b1110 "
#2026563750000
b1100 "
#2026723750000
b1000 "
#2026881250000
b0 "
#2026883750000
b1111 "
#2027043750000
b1110 "
#2027203750000
b1100 "
#2027363750000
b1000 "
#2027521250000
b0 "
#2027523750000
b1111 "
#2027683750000
b1110 "
#2027843750000
b1100 "
#2028003750000
b1000 "
#2028161250000
b0 "
#2028163750000
b1111 "
#2028323750000
b1110 "
#2028483750000
b1100 "
#2028643750000
b1000 "
#2028801250000
b0 "
#2028803750000
b1111 "
#2028963750000
b1110 "
#2029123750000
b1100 "
#2029283750000
b1000 "
#2029441250000
b0 "
#2029443750000
b1111 "
#2029603750000
b1110 "
#2029763750000
b1100 "
#2029923750000
b1000 "
#2030081250000
b0 "
#2030083750000
b1111 "
#2030243750000
b1110 "
#2030403750000
b1100 "
#2030563750000
b1000 "
#2030721250000
b0 "
#2030723750000
b1111 "
#2030883750000
b1110 "
#2031043750000
b1100 "
#2031203750000
b1000 "
#2031361250000
b0 "
#2031363750000
b1111 "
#2031523750000
b1110 "
#2031683750000
b1100 "
#2031843750000
b1000 "
#2032001250000
b0 "
#2032003750000
b1111 "
#2032163750000
b1110 "
#2032323750000
b1100 "
#2032483750000
b1000 "
#2032641250000
b0 "
#2032643750000
b1111 "
#2032803750000
b1110 "
#2032963750000
b1100 "
#2033123750000
b1000 "
#2033281250000
b0 "
#2033283750000
b1111 "
#2033443750000
b1110 "
#2033603750000
b1100 "
#2033763750000
b1000 "
#2033921250000
b0 "
#2033923750000
b1111 "
#2034083750000
b1110 "
#2034243750000
b1100 "
#2034403750000
b1000 "
#2034561250000
b0 "
#2034563750000
b1111 "
#2034723750000
b1110 "
#2034883750000
b1100 "
#2035043750000
b1000 "
#2035201250000
b0 "
#2035203750000
b1111 "
#2035363750000
b1110 "
#2035523750000
b1100 "
#2035683750000
b1000 "
#2035841250000
b0 "
#2035843750000
b1111 "
#2036003750000
b1110 "
#2036163750000
b1100 "
#2036323750000
b1000 "
#2036481250000
b0 "
#2036483750000
b1111 "
#2036643750000
b1110 "
#2036803750000
b1100 "
#2036963750000
b1000 "
#2037121250000
b0 "
#2037123750000
b1111 "
#2037283750000
b1110 "
#2037443750000
b1100 "
#2037603750000
b1000 "
#2037761250000
b0 "
#2037763750000
b1111 "
#2037923750000
b1110 "
#2038083750000
b1100 "
#2038243750000
b1000 "
#2038401250000
b0 "
#2038403750000
b1111 "
#2038563750000
b1110 "
#2038723750000
b1100 "
#2038883750000
b1000 "
#2039041250000
b0 "
#2039043750000
b1111 "
#2039203750000
b1110 "
#2039363750000
b1100 "
#2039523750000
b1000 "
#2039681250000
b0 "
#2039683750000
b1111 "
#2039843750000
b1110 "
#2040003750000
b1100 "
#2040163750000
b1000 "
#2040321250000
b0 "
#2040323750000
b1111 "
#2040483750000
b1110 "
#2040643750000
b1100 "
#2040803750000
b1000 "
#2040961250000
b0 "
#2040963750000
b1111 "
#2041123750000
b1110 "
#2041283750000
b1100 "
#2041443750000
b1000 "
#2041601250000
b0 "
#2041603750000
b1111 "
#2041763750000
b1110 "
#2041923750000
b1100 "
#2042083750000
b1000 "
#2042241250000
b0 "
#2042243750000
b1111 "
#2042403750000
b1110 "
#2042563750000
b1100 "
#2042723750000
b1000 "
#2042881250000
b0 "
#2042883750000
b1111 "
#2043043750000
b1110 "
#2043203750000
b1100 "
#2043363750000
b1000 "
#2043521250000
b0 "
#2043523750000
b1111 "
#2043683750000
b1110 "
#2043843750000
b1100 "
#2044003750000
b1000 "
#2044161250000
b0 "
#2044163750000
b1111 "
#2044323750000
b1110 "
#2044483750000
b1100 "
#2044643750000
b1000 "
#2044801250000
b0 "
#2044803750000
b1111 "
#2044963750000
b1110 "
#2045123750000
b1100 "
#2045283750000
b1000 "
#2045441250000
b0 "
#2045443750000
b1111 "
#2045603750000
b1110 "
#2045763750000
b1100 "
#2045923750000
b1000 "
#2046081250000
b0 "
#2046083750000
b1111 "
#2046243750000
b1110 "
#2046403750000
b1100 "
#2046563750000
b1000 "
#2046721250000
b0 "
#2046723750000
b1111 "
#2046883750000
b1110 "
#2047043750000
b1100 "
#2047203750000
b1000 "
#2047361250000
b0 "
#2047363750000
b1111 "
#2047523750000
b1110 "
#2047683750000
b1100 "
#2047843750000
b1000 "
#2048001250000
b0 "
#2048003750000
b1111 "
#2048163750000
b1110 "
#2048323750000
b1100 "
#2048483750000
b1000 "
#2048641250000
b0 "
#2048643750000
b1111 "
#2048803750000
b1110 "
#2048963750000
b1100 "
#2049123750000
b1000 "
#2049281250000
b0 "
#2049283750000
b1111 "
#2049443750000
b1110 "
#2049603750000
b1100 "
#2049763750000
b1000 "
#2049921250000
b0 "
#2049923750000
b1111 "
#2050083750000
b1110 "
#2050243750000
b1100 "
#2050403750000
b1000 "
#2050561250000
b0 "
#2050563750000
b1111 "
#2050723750000
b1110 "
#2050883750000
b1100 "
#2051043750000
b1000 "
#2051201250000
b0 "
#2051203750000
b1111 "
#2051363750000
b1110 "
#2051523750000
b1100 "
#2051683750000
b1000 "
#2051841250000
b0 "
#2051843750000
b1111 "
#2052003750000
b1110 "
#2052163750000
b1100 "
#2052323750000
b1000 "
#2052481250000
b0 "
#2052483750000
b1111 "
#2052643750000
b1110 "
#2052803750000
b1100 "
#2052963750000
b1000 "
#2053121250000
b0 "
#2053123750000
b1111 "
#2053283750000
b1110 "
#2053443750000
b1100 "
#2053603750000
b1000 "
#2053761250000
b0 "
#2053763750000
b1111 "
#2053923750000
b1110 "
#2054083750000
b1100 "
#2054243750000
b1000 "
#2054401250000
b0 "
#2054403750000
b1111 "
#2054563750000
b1110 "
#2054723750000
b1100 "
#2054883750000
b1000 "
#2055041250000
b0 "
#2055043750000
b1111 "
#2055203750000
b1110 "
#2055363750000
b1100 "
#2055523750000
b1000 "
#2055681250000
b0 "
#2055683750000
b1111 "
#2055843750000
b1110 "
#2056003750000
b1100 "
#2056163750000
b1000 "
#2056321250000
b0 "
#2056323750000
b1111 "
#2056483750000
b1110 "
#2056643750000
b1100 "
#2056803750000
b1000 "
#2056961250000
b0 "
#2056963750000
b1111 "
#2057123750000
b1110 "
#2057283750000
b1100 "
#2057443750000
b1000 "
#2057601250000
b0 "
#2057603750000
b1111 "
#2057763750000
b1110 "
#2057923750000
b1100 "
#2058083750000
b1000 "
#2058241250000
b0 "
#2058243750000
b1111 "
#2058403750000
b1110 "
#2058563750000
b1100 "
#2058723750000
b1000 "
#2058881250000
b0 "
#2058883750000
b1111 "
#2059043750000
b1110 "
#2059203750000
b1100 "
#2059363750000
b1000 "
#2059521250000
b0 "
#2059523750000
b1111 "
#2059683750000
b1110 "
#2059843750000
b1100 "
#2060003750000
b1000 "
#2060161250000
b0 "
#2060163750000
b1111 "
#2060323750000
b1110 "
#2060483750000
b1100 "
#2060643750000
b1000 "
#2060801250000
b0 "
#2060803750000
b1111 "
#2060963750000
b1110 "
#2061123750000
b1100 "
#2061283750000
b1000 "
#2061441250000
b0 "
#2061443750000
b1111 "
#2061603750000
b1110 "
#2061763750000
b1100 "
#2061923750000
b1000 "
#2062081250000
b0 "
#2062083750000
b1111 "
#2062243750000
b1110 "
#2062403750000
b1100 "
#2062563750000
b1000 "
#2062721250000
b0 "
#2062723750000
b1111 "
#2062883750000
b1110 "
#2063043750000
b1100 "
#2063203750000
b1000 "
#2063361250000
b0 "
#2063363750000
b1111 "
#2063523750000
b1110 "
#2063683750000
b1100 "
#2063843750000
b1000 "
#2064001250000
b0 "
#2064003750000
b1111 "
#2064163750000
b1110 "
#2064323750000
b1100 "
#2064483750000
b1000 "
#2064641250000
b0 "
#2064643750000
b1111 "
#2064803750000
b1110 "
#2064963750000
b1100 "
#2065123750000
b1000 "
#2065281250000
b0 "
#2065283750000
b1111 "
#2065443750000
b1110 "
#2065603750000
b1100 "
#2065763750000
b1000 "
#2065921250000
b0 "
#2065923750000
b1111 "
#2066083750000
b1110 "
#2066243750000
b1100 "
#2066403750000
b1000 "
#2066561250000
b0 "
#2066563750000
b1111 "
#2066723750000
b1110 "
#2066883750000
b1100 "
#2067043750000
b1000 "
#2067201250000
b0 "
#2067203750000
b1111 "
#2067363750000
b1110 "
#2067523750000
b1100 "
#2067683750000
b1000 "
#2067841250000
b0 "
#2067843750000
b1111 "
#2068003750000
b1110 "
#2068163750000
b1100 "
#2068323750000
b1000 "
#2068481250000
b0 "
#2068483750000
b1111 "
#2068643750000
b1110 "
#2068803750000
b1100 "
#2068963750000
b1000 "
#2069121250000
b0 "
#2069123750000
b1111 "
#2069283750000
b1110 "
#2069443750000
b1100 "
#2069603750000
b1000 "
#2069761250000
b0 "
#2069763750000
b1111 "
#2069923750000
b1110 "
#2070083750000
b1100 "
#2070243750000
b1000 "
#2070401250000
b0 "
#2070403750000
b1111 "
#2070563750000
b1110 "
#2070723750000
b1100 "
#2070883750000
b1000 "
#2071041250000
b0 "
#2071043750000
b1111 "
#2071203750000
b1110 "
#2071363750000
b1100 "
#2071523750000
b1000 "
#2071681250000
b0 "
#2071683750000
b1111 "
#2071843750000
b1110 "
#2072003750000
b1100 "
#2072163750000
b1000 "
#2072321250000
b0 "
#2072323750000
b1111 "
#2072483750000
b1110 "
#2072643750000
b1100 "
#2072803750000
b1000 "
#2072961250000
b0 "
#2072963750000
b1111 "
#2073123750000
b1110 "
#2073283750000
b1100 "
#2073443750000
b1000 "
#2073601250000
b0 "
#2073603750000
b1111 "
#2073763750000
b1110 "
#2073923750000
b1100 "
#2074083750000
b1000 "
#2074241250000
b0 "
#2074243750000
b1111 "
#2074403750000
b1110 "
#2074563750000
b1100 "
#2074723750000
b1000 "
#2074881250000
b0 "
#2074883750000
b1111 "
#2075043750000
b1110 "
#2075203750000
b1100 "
#2075363750000
b1000 "
#2075521250000
b0 "
#2075523750000
b1111 "
#2075683750000
b1110 "
#2075843750000
b1100 "
#2076003750000
b1000 "
#2076161250000
b0 "
#2076163750000
b1111 "
#2076323750000
b1110 "
#2076483750000
b1100 "
#2076643750000
b1000 "
#2076801250000
b0 "
#2076803750000
b1111 "
#2076963750000
b1110 "
#2077123750000
b1100 "
#2077283750000
b1000 "
#2077441250000
b0 "
#2077443750000
b1111 "
#2077603750000
b1110 "
#2077763750000
b1100 "
#2077923750000
b1000 "
#2078081250000
b0 "
#2078083750000
b1111 "
#2078243750000
b1110 "
#2078403750000
b1100 "
#2078563750000
b1000 "
#2078721250000
b0 "
#2078723750000
b1111 "
#2078883750000
b1110 "
#2079043750000
b1100 "
#2079203750000
b1000 "
#2079361250000
b0 "
#2079363750000
b1111 "
#2079523750000
b1110 "
#2079683750000
b1100 "
#2079843750000
b1000 "
#2080001250000
b0 "
#2080003750000
b1111 "
#2080163750000
b1110 "
#2080323750000
b1100 "
#2080483750000
b1000 "
#2080641250000
b0 "
#2080643750000
b1111 "
#2080803750000
b1110 "
#2080963750000
b1100 "
#2081123750000
b1000 "
#2081281250000
b0 "
#2081283750000
b1111 "
#2081443750000
b1110 "
#2081603750000
b1100 "
#2081763750000
b1000 "
#2081921250000
b0 "
#2081923750000
b1111 "
#2082083750000
b1110 "
#2082243750000
b1100 "
#2082403750000
b1000 "
#2082561250000
b0 "
#2082563750000
b1111 "
#2082723750000
b1110 "
#2082883750000
b1100 "
#2083043750000
b1000 "
#2083201250000
b0 "
#2083203750000
b1111 "
#2083363750000
b1110 "
#2083523750000
b1100 "
#2083683750000
b1000 "
#2083841250000
b0 "
#2083843750000
b1111 "
#2084003750000
b1110 "
#2084163750000
b1100 "
#2084323750000
b1000 "
#2084481250000
b0 "
#2084483750000
b1111 "
#2084643750000
b1110 "
#2084803750000
b1100 "
#2084963750000
b1000 "
#2085121250000
b0 "
#2085123750000
b1111 "
#2085283750000
b1110 "
#2085443750000
b1100 "
#2085603750000
b1000 "
#2085761250000
b0 "
#2085763750000
b1111 "
#2085923750000
b1110 "
#2086083750000
b1100 "
#2086243750000
b1000 "
#2086401250000
b0 "
#2086403750000
b1111 "
#2086563750000
b1110 "
#2086723750000
b1100 "
#2086883750000
b1000 "
#2087041250000
b0 "
#2087043750000
b1111 "
#2087203750000
b1110 "
#2087363750000
b1100 "
#2087523750000
b1000 "
#2087681250000
b0 "
#2087683750000
b1111 "
#2087843750000
b1110 "
#2088003750000
b1100 "
#2088163750000
b1000 "
#2088321250000
b0 "
#2088323750000
b1111 "
#2088483750000
b1110 "
#2088643750000
b1100 "
#2088803750000
b1000 "
#2088961250000
b0 "
#2088963750000
b1111 "
#2089123750000
b1110 "
#2089283750000
b1100 "
#2089443750000
b1000 "
#2089601250000
b0 "
#2089603750000
b1111 "
#2089763750000
b1110 "
#2089923750000
b1100 "
#2090083750000
b1000 "
#2090241250000
b0 "
#2090243750000
b1111 "
#2090403750000
b1110 "
#2090563750000
b1100 "
#2090723750000
b1000 "
#2090881250000
b0 "
#2090883750000
b1111 "
#2091043750000
b1110 "
#2091203750000
b1100 "
#2091363750000
b1000 "
#2091521250000
b0 "
#2091523750000
b1111 "
#2091683750000
b1110 "
#2091843750000
b1100 "
#2092003750000
b1000 "
#2092161250000
b0 "
#2092163750000
b1111 "
#2092323750000
b1110 "
#2092483750000
b1100 "
#2092643750000
b1000 "
#2092801250000
b0 "
#2092803750000
b1111 "
#2092963750000
b1110 "
#2093123750000
b1100 "
#2093283750000
b1000 "
#2093441250000
b0 "
#2093443750000
b1111 "
#2093603750000
b1110 "
#2093763750000
b1100 "
#2093923750000
b1000 "
#2094081250000
b0 "
#2094083750000
b1111 "
#2094243750000
b1110 "
#2094403750000
b1100 "
#2094563750000
b1000 "
#2094721250000
b0 "
#2094723750000
b1111 "
#2094883750000
b1110 "
#2095043750000
b1100 "
#2095203750000
b1000 "
#2095361250000
b0 "
#2095363750000
b1111 "
#2095523750000
b1110 "
#2095683750000
b1100 "
#2095843750000
b1000 "
#2096001250000
b0 "
#2096003750000
b1111 "
#2096163750000
b1110 "
#2096323750000
b1100 "
#2096483750000
b1000 "
#2096641250000
b0 "
#2096643750000
b1111 "
#2096803750000
b1110 "
#2096963750000
b1100 "
#2097123750000
b1000 "
#2097281250000
b0 "
#2097283750000
b1111 "
#2097443750000
b1110 "
#2097603750000
b1100 "
#2097763750000
b1000 "
#2097921250000
b0 "
#2097923750000
b1111 "
#2098083750000
b1110 "
#2098243750000
b1100 "
#2098403750000
b1000 "
#2098561250000
b0 "
#2098563750000
b1111 "
#2098723750000
b1110 "
#2098883750000
b1100 "
#2099043750000
b1000 "
#2099201250000
b0 "
#2099203750000
b1111 "
#2099363750000
b1110 "
#2099523750000
b1100 "
#2099683750000
b1000 "
#2099841250000
b0 "
#2099843750000
b1111 "
#2100003750000
b1110 "
#2100163750000
b1100 "
#2100323750000
b1000 "
#2100481250000
b0 "
